pyconstrobe/__init__.py
pyconstrobe/process_manager.py
pyconstrobe-1.0.1.dist-info/LICENSE
pyconstrobe-1.0.1.dist-info/METADATA
pyconstrobe-1.0.1.dist-info/WHEEL
pyconstrobe-1.0.1.dist-info/top_level.txt
pyconstrobe-1.0.1.dist-info/RECORD
